qfitswidget/__init__.py
qfitswidget/navigationtoolbar.py
qfitswidget/norm.py
qfitswidget/py.typed
qfitswidget/qfitswidget.py
qfitswidget/settings.py
qfitswidget/qt/__init__.py
qfitswidget/qt/fitswidget.py
qfitswidget/qt/fitswidget.ui
qfitswidget/qt/resources.py
qfitswidget/qt/resources.rc
qfitswidget/qt/settings.py
qfitswidget/qt/settings.ui
qfitswidget/qt/resources/image-solid.svg
qfitswidget-0.12.2.dist-info/METADATA
qfitswidget-0.12.2.dist-info/WHEEL
qfitswidget-0.12.2.dist-info/licenses/LICENSE
qfitswidget-0.12.2.dist-info/RECORD
