Metadata-Version: 2.4
Name: qfitswidget
Version: 0.12.2
Summary: PyQt widget for displaying FITS files
Author-email: Tim-Oliver Husser <thusser@uni-goettingen.de>
License-Expression: MIT
License-File: LICENSE
Requires-Python: <3.14,>=3.11
Requires-Dist: astropy<8,>=7.0.1
Requires-Dist: jinja2<4,>=3.1.4
Requires-Dist: matplotlib<4,>=3.10.1
Requires-Dist: numpy<3,>=2.2.5
Requires-Dist: opencv-python-headless<5,>=4.10.0.84
Requires-Dist: pyqt5<6,>=5.15.11
